{"Availability": "", "Beer": "Back in Black", "Brewery": "21st Amendment", "Establishments": "", "Style": "Black IPA", "State": "CA", "Dates": "", "Checkin": "True", "highlight": "", "City": "San Francisco", "Distribution": ""}
{"Availability": "", "Beer": "Preserved Lemon Gose", "Brewery": "4 Hands", "Establishments": "", "Style": "Gose", "State": "MO", "Dates": "", "Checkin": "False", "highlight": "", "City": "St. Louis", "Distribution": ""}
{"Availability": "", "Beer": "Purple Haze", "Brewery": "Abita", "Establishments": "", "Style": "Whit", "State": "LA", "Dates": "", "Checkin": "True", "highlight": "", "City": "Abita Springs", "Distribution": ""}
{"Availability": "", "Beer": "35K", "Brewery": "Against the Grain", "Establishments": "", "Style": "Stout", "State": "KY", "Dates": "", "Checkin": "True", "highlight": "", "City": "Louisville", "Distribution": ""}
{"Availability": "", "Beer": "Winter Ale", "Brewery": "Alaskan", "Establishments": "", "Style": "Winter/Christmas", "State": "AK", "Dates": "", "Checkin": "False", "highlight": "", "City": "Juneau", "Distribution": ""}
{"Availability": "", "Beer": "Pure Hoppiness", "Brewery": "Alpine", "Establishments": "", "Style": "IPA", "State": "CA", "Dates": "", "Checkin": "True", "highlight": "", "City": "Alpine", "Distribution": ""}
{"Availability": "", "Beer": "Anadramous", "Brewery": "Anchorage", "Establishments": "", "Style": "Barrel Aged", "State": "AK", "Dates": "", "Checkin": "False", "highlight": "", "City": "Anchorage", "Distribution": ""}
{"Availability": "", "Beer": "Blood Orange Gose", "Brewery": "Anderson Valley", "Establishments": "", "Style": "Gose", "State": "CA", "Dates": "", "Checkin": "True", "highlight": "", "City": "Boonville", "Distribution": ""}
{"Availability": "", "Beer": "Rowdy", "Brewery": "Atlas", "Establishments": "", "Style": "Rye", "State": "DC", "Dates": "", "Checkin": "True", "highlight": "", "City": "Washington", "Distribution": ""}
{"Availability": "", "Beer": "Paw Paw's Peach Wheat", "Brewery": "Back Forty", "Establishments": "", "Style": "Fruit", "State": "AL", "Dates": "", "Checkin": "True", "highlight": "", "City": "Gadsden", "Distribution": ""}
{"Availability": "", "Beer": "Grapefruit Sculpin", "Brewery": "Ballast Point", "Establishments": "", "Style": "Fruit", "State": "CA", "Dates": "", "Checkin": "True", "highlight": "", "City": "San Diego", "Distribution": ""}
{"Availability": "", "Beer": "Two Hearted", "Brewery": "Bell's", "Establishments": "", "Style": "IPA", "State": "MI", "Dates": "", "Checkin": "True", "highlight": "", "City": "Kalamazoo", "Distribution": ""}
{"Availability": "", "Beer": "Oberon", "Brewery": "Bell's", "Establishments": "", "Style": "Summer", "State": "MI", "Dates": "", "Checkin": "True", "highlight": "", "City": "Kalamazoo", "Distribution": ""}
{"Availability": "", "Beer": "Powder Hound", "Brewery": "Big Sky", "Establishments": "", "Style": "Winter/Christmas", "State": "MT", "Dates": "", "Checkin": "False", "highlight": "", "City": "Missoula", "Distribution": ""}
{"Availability": "", "Beer": "Chocolate Ale", "Brewery": "Boulevard", "Establishments": "", "Style": "Chocolate", "State": "MO", "Dates": "", "Checkin": "True", "highlight": "", "City": "Kansas City", "Distribution": ""}
{"Availability": "", "Beer": "Tank 7", "Brewery": "Boulevard", "Establishments": "", "Style": "Farmhouse/Saison", "State": "MO", "Dates": "", "Checkin": "True", "highlight": "", "City": "Kansas City", "Distribution": ""}
{"Availability": "", "Beer": "471 IPA Barrel Series", "Brewery": "Breckenridge", "Establishments": "", "Style": "Barrel Aged", "State": "CO", "Dates": "", "Checkin": "True", "highlight": "", "City": "Breckenridge", "Distribution": ""}
{"Availability": "", "Beer": "Sorachi Ace", "Brewery": "Brooklyn", "Establishments": "", "Style": "Farmhouse/Saison", "State": "NY", "Dates": "", "Checkin": "True", "highlight": "", "City": "Brooklyn", "Distribution": ""}
{"Availability": "", "Beer": "Lager", "Brewery": "Brooklyn", "Establishments": "", "Style": "Lager", "State": "NY", "Dates": "", "Checkin": "True", "highlight": "", "City": "Brooklyn", "Distribution": ""}
{"Availability": "", "Beer": "Skillet Donut Stout", "Brewery": "Burial Beer", "Establishments": "", "Style": "Stout", "State": "NC", "Dates": "", "Checkin": "False", "highlight": "", "City": "Asheville", "Distribution": ""}
{"Availability": "", "Beer": "Jai Alai", "Brewery": "Cigar City", "Establishments": "", "Style": "IPA", "State": "FL", "Dates": "", "Checkin": "True", "highlight": "", "City": "Tampa", "Distribution": ""}
{"Availability": "", "Beer": "Pile o' Dirt", "Brewery": "Crow Peak", "Establishments": "", "Style": "Porter", "State": "SD", "Dates": "", "Checkin": "False", "highlight": "", "City": "Spearfish", "Distribution": ""}
{"Availability": "", "Beer": "On the Wings of Armegeddon", "Brewery": "DC Brau", "Establishments": "", "Style": "dIPA", "State": "DC", "Dates": "", "Checkin": "True", "highlight": "", "City": "Washington", "Distribution": ""}
{"Availability": "", "Beer": "Mirror Pond", "Brewery": "Deschutes", "Establishments": "", "Style": "American Pale", "State": "OR", "Dates": "", "Checkin": "False", "highlight": "", "City": "Bend", "Distribution": ""}
{"Availability": "", "Beer": "Jubelale", "Brewery": "Deschutes", "Establishments": "", "Style": "Winter/Christmas", "State": "OR", "Dates": "", "Checkin": "False", "highlight": "", "City": "Bend", "Distribution": ""}
{"Availability": "", "Beer": "Vienna Lager", "Brewery": "Devil's Backbone", "Establishments": "", "Style": "Lager", "State": "VA", "Dates": "", "Checkin": "True", "highlight": "", "City": "Roseland", "Distribution": ""}
{"Availability": "", "Beer": "90 Minute IPA", "Brewery": "Dogfish Head", "Establishments": "", "Style": "dIPA", "State": "DE", "Dates": "", "Checkin": "True", "highlight": "", "City": "Milton", "Distribution": ""}
{"Availability": "", "Beer": "Festina Peche", "Brewery": "Dogfish Head", "Establishments": "", "Style": "Sour", "State": "DE", "Dates": "", "Checkin": "True", "highlight": "", "City": "Milton", "Distribution": ""}
{"Availability": "", "Beer": "Milk Stout", "Brewery": "Duck-Rabbit", "Establishments": "", "Style": "Stout", "State": "NC", "Dates": "", "Checkin": "True", "highlight": "", "City": "Farmville", "Distribution": ""}
{"Availability": "", "Beer": "Night Owl", "Brewery": "Elysian", "Establishments": "", "Style": "Fall/Pumpkin", "State": "WA", "Dates": "", "Checkin": "False", "highlight": "", "City": "Seattle", "Distribution": ""}
{"Availability": "", "Beer": "Sour Bikini", "Brewery": "Evil Twin", "Establishments": "", "Style": "Sour", "State": "NY", "Dates": "", "Checkin": "True", "highlight": "", "City": "Brooklyn", "Distribution": ""}
{"Availability": "", "Beer": "Wood Chipper", "Brewery": "Fargo", "Establishments": "", "Style": "IPA", "State": "ND", "Dates": "", "Checkin": "False", "highlight": "", "City": "Fargo", "Distribution": ""}
{"Availability": "", "Beer": "Farmhouse Summer", "Brewery": "Flying Fish", "Establishments": "", "Style": "Summer", "State": "NJ", "Dates": "", "Checkin": "False", "highlight": "", "City": "Somerdale", "Distribution": ""}
{"Availability": "", "Beer": "Sexual Chocolate", "Brewery": "Foothills", "Establishments": "", "Style": "Chocolate", "State": "NC", "Dates": "", "Checkin": "True", "highlight": "", "City": "Winston-Salem", "Distribution": ""}
{"Availability": "", "Beer": "Java the Hop", "Brewery": "Fort George", "Establishments": "", "Style": "Breakfast", "State": "OR", "Dates": "", "Checkin": "False", "highlight": "", "City": "Astoria", "Distribution": ""}
{"Availability": "", "Beer": "Kentucky Breakfast Stout (KBS)", "Brewery": "Founders", "Establishments": "", "Style": "Breakfast", "State": "MI", "Dates": "", "Checkin": "True", "highlight": "", "City": "Grand Rapids", "Distribution": ""}
{"Availability": "", "Beer": "Bonfire", "Brewery": "Fremont", "Establishments": "", "Style": "Rye", "State": "WA", "Dates": "", "Checkin": "False", "highlight": "", "City": "Seattle", "Distribution": ""}
{"Availability": "", "Beer": "Sweet Potato Casserole", "Brewery": "Funky Buddha", "Establishments": "", "Style": "Fall/Pumpkin", "State": "FL", "Dates": "", "Checkin": "True", "highlight": "", "City": "Oakland Park", "Distribution": ""}
{"Availability": "", "Beer": "Bourbon County Brand Coffee Stout", "Brewery": "Goose Island", "Establishments": "", "Style": "Barrel Aged", "State": "IL", "Dates": "", "Checkin": "True", "highlight": "", "City": "Chicago", "Distribution": ""}
{"Availability": "", "Beer": "Sofie", "Brewery": "Goose Island", "Establishments": "", "Style": "Barrel Aged", "State": "IL", "Dates": "", "Checkin": "False", "highlight": "", "City": "Chicago", "Distribution": ""}
{"Availability": "", "Beer": "Amber Ale", "Brewery": "Grand Teton", "Establishments": "", "Style": "Amber", "State": "ID", "Dates": "", "Checkin": "False", "highlight": "", "City": "Victor", "Distribution": ""}
{"Availability": "", "Beer": "Chocolate Oak Aged Yeti", "Brewery": "Great Divide", "Establishments": "", "Style": "Chocolate", "State": "CO", "Dates": "", "Checkin": "True", "highlight": "", "City": "Denver", "Distribution": ""}
{"Availability": "", "Beer": "Edmund Fitzgerald", "Brewery": "Great Lakes", "Establishments": "", "Style": "Porter", "State": "OH", "Dates": "", "Checkin": "True", "highlight": "", "City": "Cleveland", "Distribution": ""}
{"Availability": "", "Beer": "Mothman Black IPA", "Brewery": "Greenbrier Valley", "Establishments": "", "Style": "Black IPA", "State": "WV", "Dates": "", "Checkin": "False", "highlight": "", "City": "Maxwelton", "Distribution": ""}
{"Availability": "", "Beer": "Daisy Cutter", "Brewery": "Half Acre", "Establishments": "", "Style": "American Pale", "State": "IL", "Dates": "", "Checkin": "True", "highlight": "", "City": "Chicago", "Distribution": ""}
{"Availability": "", "Beer": "Gingerbread Stout", "Brewery": "Hardywood", "Establishments": "", "Style": "Stout", "State": "VA", "Dates": "", "Checkin": "True", "highlight": "", "City": "Richmond", "Distribution": ""}
{"Availability": "", "Beer": "Edward", "Brewery": "Hill Farmstead", "Establishments": "", "Style": "American Pale", "State": "VT", "Dates": "", "Checkin": "True", "highlight": "", "City": "Greensboro", "Distribution": ""}
{"Availability": "", "Beer": "The One They Call Zoe", "Brewery": "Hops & Grain", "Establishments": "", "Style": "Lager", "State": "TX", "Dates": "", "Checkin": "False", "highlight": "", "City": "Austin", "Distribution": ""}
{"Availability": "", "Beer": "Secession", "Brewery": "Hopworks Urban Brewery", "Establishments": "", "Style": "Black IPA", "State": "OR", "Dates": "", "Checkin": "False", "highlight": "", "City": "Portland", "Distribution": ""}
{"Availability": "", "Beer": "Noel de Calabaza", "Brewery": "Jolly Pumpkin", "Establishments": "", "Style": "Winter/Christmas", "State": "MI", "Dates": "", "Checkin": "True", "highlight": "", "City": "Dexter", "Distribution": ""}
{"Availability": "", "Beer": "American Flyer", "Brewery": "Joseph James", "Establishments": "", "Style": "Lager", "State": "NV", "Dates": "", "Checkin": "False", "highlight": "", "City": "Henderson", "Distribution": ""}
{"Availability": "", "Beer": "Southern Pecan", "Brewery": "Lazy Magnolia", "Establishments": "", "Style": "Fall/Pumpkin", "State": "MS", "Dates": "", "Checkin": "True", "highlight": "", "City": "Kiln", "Distribution": ""}
{"Availability": "", "Beer": "The Disaster at Meux", "Brewery": "Lion Bridge", "Establishments": "", "Style": "Porter", "State": "IA", "Dates": "", "Checkin": "False", "highlight": "", "City": "Cedar Rapids", "Distribution": ""}
{"Availability": "", "Beer": "Raspberry Brown", "Brewery": "Lost Coast", "Establishments": "", "Style": "Fruit", "State": "CA", "Dates": "", "Checkin": "True", "highlight": "", "City": "Eureka", "Distribution": ""}
{"Availability": "", "Beer": "Zoe", "Brewery": "Maine", "Establishments": "", "Style": "Amber", "State": "ME", "Dates": "", "Checkin": "True", "highlight": "", "City": "Freeport", "Distribution": ""}
{"Availability": "", "Beer": "Day Break", "Brewery": "Martin House", "Establishments": "", "Style": "Breakfast", "State": "TX", "Dates": "", "Checkin": "False", "highlight": "", "City": "Fort Worth", "Distribution": ""}
{"Availability": "", "Beer": "Coconut Porter", "Brewery": "Maui", "Establishments": "", "Style": "Porter", "State": "HI", "Dates": "", "Checkin": "True", "highlight": "", "City": "Maui", "Distribution": ""}
{"Availability": "", "Beer": "Almost Heaven", "Brewery": "Mountain State Brewing", "Establishments": "", "Style": "Amber", "State": "WV", "Dates": "", "Checkin": "False", "highlight": "", "City": "Thomas", "Distribution": ""}
{"Availability": "", "Beer": "Autocrat Coffee Milk Stout", "Brewery": "Narragansett", "Establishments": "", "Style": "Breakfast", "State": "RI", "Dates": "", "Checkin": "True", "highlight": "", "City": "Providence", "Distribution": ""}
{"Availability": "", "Beer": "Melange a Trois", "Brewery": "Nebraska Brewing", "Establishments": "", "Style": "Barrel Aged", "State": "NE", "Dates": "", "Checkin": "True", "highlight": "", "City": "Omaha", "Distribution": ""}
{"Availability": "", "Beer": "Fat Tire", "Brewery": "New Belgium", "Establishments": "", "Style": "Amber", "State": "CO", "Dates": "", "Checkin": "True", "highlight": "", "City": "Ft. Collins", "Distribution": ""}
{"Availability": "", "Beer": "Le Terroir", "Brewery": "New Belgium", "Establishments": "", "Style": "Sour", "State": "CO", "Dates": "", "Checkin": "True", "highlight": "", "City": "Ft. Collins", "Distribution": ""}
{"Availability": "", "Beer": "Fuzzy Baby Ducks", "Brewery": "New England", "Establishments": "", "Style": "IPA", "State": "CT", "Dates": "", "Checkin": "False", "highlight": "", "City": "Woodbridge", "Distribution": ""}
{"Availability": "", "Beer": "Spotted Cow", "Brewery": "New Glarus", "Establishments": "", "Style": "Farmhouse/Saison", "State": "WI", "Dates": "", "Checkin": "False", "highlight": "", "City": "New Glarus", "Distribution": ""}
{"Availability": "", "Beer": "Dragon's Milk", "Brewery": "New Holland", "Establishments": "", "Style": "Barrel Aged", "State": "MI", "Dates": "", "Checkin": "True", "highlight": "", "City": "Holland", "Distribution": ""}
{"Availability": "", "Beer": "Tricerahops", "Brewery": "Ninkasi", "Establishments": "", "Style": "dIPA", "State": "OR", "Dates": "", "Checkin": "True", "highlight": "", "City": "Eugene", "Distribution": ""}
{"Availability": "", "Beer": "Jet Star", "Brewery": "NoLi", "Establishments": "", "Style": "dIPA", "State": "WA", "Dates": "", "Checkin": "False", "highlight": "", "City": "Spokane", "Distribution": ""}
{"Availability": "", "Beer": "St. Lupulin", "Brewery": "Odell", "Establishments": "", "Style": "Summer", "State": "CO", "Dates": "", "Checkin": "False", "highlight": "", "City": "Fort Collins", "Distribution": ""}
{"Availability": "", "Beer": "Troublesome", "Brewery": "Off Color", "Establishments": "", "Style": "Gose", "State": "IL", "Dates": "", "Checkin": "False", "highlight": "", "City": "Chicago", "Distribution": ""}
{"Availability": "", "Beer": "Hennepin", "Brewery": "Ommegang", "Establishments": "", "Style": "Farmhouse/Saison", "State": "NY", "Dates": "", "Checkin": "True", "highlight": "", "City": "Cooperstown", "Distribution": ""}
{"Availability": "", "Beer": "Fleur de Houblon", "Brewery": "Ommegang", "Establishments": "", "Style": "Summer", "State": "NY", "Dates": "", "Checkin": "True", "highlight": "", "City": "Cooperstown", "Distribution": ""}
{"Availability": "", "Beer": "The Maple Collaboration", "Brewery": "Peak Organic", "Establishments": "", "Style": "Breakfast", "State": "ME", "Dates": "", "Checkin": "False", "highlight": "", "City": "Portland", "Distribution": ""}
{"Availability": "", "Beer": "Optimal Wit", "Brewery": "Port City", "Establishments": "", "Style": "Whit", "State": "VA", "Dates": "", "Checkin": "True", "highlight": "", "City": "Alexandria", "Distribution": ""}
{"Availability": "", "Beer": "Funky Gold Mosaic", "Brewery": "Prarie Artisan Ales", "Establishments": "", "Style": "Sour", "State": "OK", "Dates": "", "Checkin": "True", "highlight": "", "City": "Tulsa", "Distribution": ""}
{"Availability": "", "Beer": "VooDoo Doughnut Bacon Maple", "Brewery": "Rogue", "Establishments": "", "Style": "Breakfast", "State": "OR", "Dates": "", "Checkin": "False", "highlight": "", "City": "Newport", "Distribution": ""}
{"Availability": "", "Beer": "Shakespeare Oatmeal Stout", "Brewery": "Rogue", "Establishments": "", "Style": "Breakfast", "State": "OR", "Dates": "", "Checkin": "False", "highlight": "", "City": "Newport", "Distribution": ""}
{"Availability": "", "Beer": "Hefeweizen", "Brewery": "Santa Fe", "Establishments": "", "Style": "Whit", "State": "NM", "Dates": "", "Checkin": "False", "highlight": "", "City": "Santa Fe", "Distribution": ""}
{"Availability": "", "Beer": "Chocolate Hefe", "Brewery": "Secret Engine", "Establishments": "", "Style": "Chocolate", "State": "NY", "Dates": "", "Checkin": "False", "highlight": "", "City": "Brooklyn", "Distribution": ""}
{"Availability": "", "Beer": "Ruby Redbird", "Brewery": "Shiner", "Establishments": "", "Style": "Fruit", "State": "TX", "Dates": "", "Checkin": "True", "highlight": "", "City": "Shiner", "Distribution": ""}
{"Availability": "", "Beer": "Pumpkinhead", "Brewery": "Shipyard", "Establishments": "", "Style": "Fall/Pumpkin", "State": "ME", "Dates": "", "Checkin": "True", "highlight": "", "City": "Portland", "Distribution": ""}
{"Availability": "", "Beer": "Pale Ale", "Brewery": "Sierra Nevada", "Establishments": "", "Style": "American Pale", "State": "CA", "Dates": "", "Checkin": "True", "highlight": "", "City": "Chico", "Distribution": ""}
{"Availability": "", "Beer": "Flower Envy Saison", "Brewery": "Slumbrew", "Establishments": "", "Style": "Farmhouse/Saison", "State": "MA", "Dates": "", "Checkin": "False", "highlight": "", "City": "Somerville", "Distribution": ""}
{"Availability": "", "Beer": "Rhye IPA", "Brewery": "Smuttynose", "Establishments": "", "Style": "Rye", "State": "NH", "Dates": "", "Checkin": "True", "highlight": "", "City": "Hampton", "Distribution": ""}
{"Availability": "", "Beer": "Zonker", "Brewery": "Snake River", "Establishments": "", "Style": "Stout", "State": "WY", "Dates": "", "Checkin": "True", "highlight": "", "City": "Jackson", "Distribution": ""}
{"Availability": "", "Beer": "Shakedown", "Brewery": "Starr Hill", "Establishments": "", "Style": "Chocolate", "State": "VA", "Dates": "", "Checkin": "True", "highlight": "", "City": "Crozet", "Distribution": ""}
{"Availability": "", "Beer": "Gose Gone Wild", "Brewery": "Stillwater Artisanal", "Establishments": "", "Style": "Gose", "State": "MD", "Dates": "", "Checkin": "True", "highlight": "", "City": "Baltimore", "Distribution": ""}
{"Availability": "", "Beer": "Enjoy By (Black IPA)", "Brewery": "Stone", "Establishments": "", "Style": "Black IPA", "State": "CA", "Dates": "", "Checkin": "True", "highlight": "", "City": "San Diego", "Distribution": ""}
{"Availability": "", "Beer": "Hell", "Brewery": "Surly", "Establishments": "", "Style": "Lager", "State": "MN", "Dates": "", "Checkin": "True", "highlight": "", "City": "Minneapolis", "Distribution": ""}
{"Availability": "", "Beer": "Waterkeeper Hefeweizen", "Brewery": "SweetWater", "Establishments": "", "Style": "Whit", "State": "GA", "Dates": "", "Checkin": "False", "highlight": "", "City": "Atlanta", "Distribution": ""}
{"Availability": "", "Beer": "Ginger Peach Saison", "Brewery": "Tallgrass", "Establishments": "", "Style": "Fruit", "State": "KS", "Dates": "", "Checkin": "False", "highlight": "", "City": "Manhattan", "Distribution": ""}
{"Availability": "", "Beer": "Raspberry Jam", "Brewery": "Tallgrass", "Establishments": "", "Style": "Fruit", "State": "KS", "Dates": "", "Checkin": "False", "highlight": "", "City": "Manhattan", "Distribution": ""}
{"Availability": "", "Beer": "Rye Pale Ale", "Brewery": "Terrapin", "Establishments": "", "Style": "Rye", "State": "GA", "Dates": "", "Checkin": "True", "highlight": "", "City": "Athens", "Distribution": ""}
{"Availability": "", "Beer": "Zombie Dust", "Brewery": "Three Floyds", "Establishments": "", "Style": "American Pale", "State": "IN", "Dates": "", "Checkin": "True", "highlight": "", "City": "Munster", "Distribution": ""}
{"Availability": "", "Beer": "Master of Pumpkins", "Brewery": "Troegs", "Establishments": "", "Style": "Fall/Pumpkin", "State": "PA", "Dates": "", "Checkin": "False", "highlight": "", "City": "Hershey", "Distribution": ""}
{"Availability": "", "Beer": "Cane and Ebel", "Brewery": "Two Brothers", "Establishments": "", "Style": "Rye", "State": "IL", "Dates": "", "Checkin": "True", "highlight": "", "City": "Warrenville", "Distribution": ""}
{"Availability": "", "Beer": "Black Hops Tactical IPA", "Brewery": "Uberbrew", "Establishments": "", "Style": "Black IPA", "State": "MT", "Dates": "", "Checkin": "False", "highlight": "", "City": "Billings", "Distribution": ""}
{"Availability": "", "Beer": "Birthday Suit", "Brewery": "Uinta", "Establishments": "", "Style": "Sour", "State": "UT", "Dates": "", "Checkin": "True", "highlight": "", "City": "Salt Lake City", "Distribution": ""}
{"Availability": "", "Beer": "Christmas", "Brewery": "Upslope", "Establishments": "", "Style": "Winter/Christmas", "State": "CO", "Dates": "", "Checkin": "False", "highlight": "", "City": "Boulder", "Distribution": ""}
{"Availability": "", "Beer": "Kirsch Gose", "Brewery": "Victory", "Establishments": "", "Style": "Gose", "State": "PA", "Dates": "", "Checkin": "True", "highlight": "", "City": "Downington", "Distribution": ""}
{"Availability": "", "Beer": "Summer Love", "Brewery": "Victory", "Establishments": "", "Style": "Summer", "State": "PA", "Dates": "", "Checkin": "True", "highlight": "", "City": "Downington", "Distribution": ""}
{"Availability": "", "Beer": "Polygamy Porter", "Brewery": "Wasatch", "Establishments": "", "Style": "Porter", "State": "UT", "Dates": "", "Checkin": "False", "highlight": "", "City": "Park City", "Distribution": ""}
{"Availability": "", "Beer": "Gose", "Brewery": "Westbrook", "Establishments": "", "Style": "Gose", "State": "SC", "Dates": "", "Checkin": "True", "highlight": "", "City": "Mt. Pleasant", "Distribution": ""}
{"Availability": "", "Beer": "Freak of Nature", "Brewery": "Wicked Weed", "Establishments": "", "Style": "dIPA", "State": "NC", "Dates": "", "Checkin": "True", "highlight": "", "City": "Asheville", "Distribution": ""}
{"Availability": "", "Beer": "Hefeweizen", "Brewery": "Widmer Brothers", "Establishments": "", "Style": "Whit", "State": "OR", "Dates": "", "Checkin": "True", "highlight": "", "City": "Portland", "Distribution": ""}
{"Availability": "", "Beer": "Gerst Amber", "Brewery": "Yazoo", "Establishments": "", "Style": "Amber", "State": "TN", "Dates": "", "Checkin": "False", "highlight": "", "City": "Nashville", "Distribution": ""}
