{"City": "Victor", "Availability": "", "Establishments": "", "Checkin": "False", "Distribution": "", "Beer": "Amber Ale", "Dates": "", "State": "ID", "Brewery": "Grand Teton", "Style": "Amber"}|{"City": "Nashville", "Availability": "", "Establishments": "", "Checkin": "False", "Distribution": "", "Beer": "Gerst Amber", "Dates": "", "State": "TN", "Brewery": "Yazoo", "Style": "Amber"}|{"City": "Thomas", "Availability": "", "Establishments": "", "Checkin": "False", "Distribution": "", "Beer": "Almost Heaven", "Dates": "", "State": "WV", "Brewery": "Mountain State Brewing", "Style": "Amber"}|{"City": "Bend", "Availability": "", "Establishments": "", "Checkin": "False", "Distribution": "", "Beer": "Mirror Pond", "Dates": "", "State": "OR", "Brewery": "Deschutes", "Style": "American Pale"}|{"City": "Greensboro", "Availability": "", "Establishments": "", "Checkin": "False", "Distribution": "", "Beer": "Edward", "Dates": "", "State": "VT", "Brewery": "Hill Farmstead", "Style": "American Pale"}|{"City": "Anchorage", "Availability": "", "Establishments": "", "Checkin": "False", "Distribution": "", "Beer": "Anadramous", "Dates": "", "State": "AK", "Brewery": "Anchorage", "Style": "Barrel Aged"}|{"City": "Omaha", "Availability": "", "Establishments": "", "Checkin": "False", "Distribution": "", "Beer": "Melange a Trois", "Dates": "", "State": "NE", "Brewery": "Nebraska Brewing", "Style": "Barrel Aged"}|{"City": "San Diego", "Availability": "", "Establishments": "", "Checkin": "False", "Distribution": "", "Beer": "Enjoy By (Black IPA)", "Dates": "", "State": "CA", "Brewery": "Stone", "Style": "Black IPA"}|{"City": "Billings", "Availability": "", "Establishments": "", "Checkin": "False", "Distribution": "", "Beer": "Black Hops Tactical IPA", "Dates": "", "State": "MT", "Brewery": "Uberbrew", "Style": "Black IPA"}|{"City": "Portland", "Availability": "", "Establishments": "", "Checkin": "False", "Distribution": "", "Beer": "Secession", "Dates": "", "State": "OR", "Brewery": "Hopworks Urban Brewery", "Style": "Black IPA"}|{"City": "Maxwelton", "Availability": "", "Establishments": "", "Checkin": "False", "Distribution": "", "Beer": "Mothman Black IPA", "Dates": "", "State": "WV", "Brewery": "Greenbrier Valley", "Style": "Black IPA"}|{"City": "Portland", "Availability": "", "Establishments": "", "Checkin": "False", "Distribution": "", "Beer": "The Maple Collaboration", "Dates": "", "State": "ME", "Brewery": "Peak Organic", "Style": "Breakfast"}|{"City": "Astoria", "Availability": "", "Establishments": "", "Checkin": "False", "Distribution": "", "Beer": "Java the Hop", "Dates": "", "State": "OR", "Brewery": "Fort George", "Style": "Breakfast"}|{"City": "Newport", "Availability": "", "Establishments": "", "Checkin": "False", "Distribution": "", "Beer": "VooDoo Doughnut Bacon Maple", "Dates": "", "State": "OR", "Brewery": "Rogue", "Style": "Breakfast"}|{"City": "Winston-Salem", "Availability": "", "Establishments": "", "Checkin": "False", "Distribution": "", "Beer": "Sexual Chocolate", "Dates": "", "State": "NC", "Brewery": "Foothills", "Style": "Chocolate"}|{"City": "Brooklyn", "Availability": "", "Establishments": "", "Checkin": "False", "Distribution": "", "Beer": "Chocolate Hefe", "Dates": "", "State": "NY", "Brewery": "Secret Engine", "Style": "Chocolate"}|{"City": "Washington", "Availability": "", "Establishments": "", "Checkin": "False", "Distribution": "", "Beer": "On the Wings of Armegeddon", "Dates": "", "State": "DC", "Brewery": "DC Brau", "Style": "dIPA"}|{"City": "Asheville", "Availability": "", "Establishments": "", "Checkin": "False", "Distribution": "", "Beer": "Freak of Nature", "Dates": "", "State": "NC", "Brewery": "Wicked Weed", "Style": "dIPA"}|{"City": "Eugene", "Availability": "", "Establishments": "", "Checkin": "False", "Distribution": "", "Beer": "Tricerahops", "Dates": "", "State": "OR", "Brewery": "Ninkasi", "Style": "dIPA"}|{"City": "Spokane", "Availability": "", "Establishments": "", "Checkin": "False", "Distribution": "", "Beer": "Jet Star", "Dates": "", "State": "WA", "Brewery": "NoLi", "Style": "dIPA"}|{"City": "Hershey", "Availability": "", "Establishments": "", "Checkin": "False", "Distribution": "", "Beer": "Master of Pumpkins", "Dates": "", "State": "PA", "Brewery": "Troegs", "Style": "Fall/Pumpkin"}|{"City": "Seattle", "Availability": "", "Establishments": "", "Checkin": "False", "Distribution": "", "Beer": "Night Owl", "Dates": "", "State": "WA", "Brewery": "Elysian", "Style": "Fall/Pumpkin"}|{"City": "Somerville", "Availability": "", "Establishments": "", "Checkin": "False", "Distribution": "", "Beer": "Flower Envy Saison", "Dates": "", "State": "MA", "Brewery": "Slumbrew", "Style": "Farmhouse/Saison"}|{"City": "New Glarus", "Availability": "", "Establishments": "", "Checkin": "False", "Distribution": "", "Beer": "Spotted Cow", "Dates": "", "State": "WI", "Brewery": "New Glarus", "Style": "Farmhouse/Saison"}|{"City": "Gadsden", "Availability": "", "Establishments": "", "Checkin": "False", "Distribution": "", "Beer": "Paw Paw's Peach Wheat", "Dates": "", "State": "AL", "Brewery": "Back Forty", "Style": "Fruit"}|{"City": "Manhattan", "Availability": "", "Establishments": "", "Checkin": "False", "Distribution": "", "Beer": "Ginger Peach Saison", "Dates": "", "State": "KS", "Brewery": "Tallgrass", "Style": "Fruit"}|{"City": "St. Louis", "Availability": "", "Establishments": "", "Checkin": "False", "Distribution": "", "Beer": "Preserved Lemon Gose", "Dates": "", "State": "MO", "Brewery": "4 Hands", "Style": "Gose"}|{"City": "Downington", "Availability": "", "Establishments": "", "Checkin": "False", "Distribution": "", "Beer": "Kirsch Gose", "Dates": "", "State": "PA", "Brewery": "Victory", "Style": "Gose"}|{"City": "Mt. Pleasant", "Availability": "", "Establishments": "", "Checkin": "False", "Distribution": "", "Beer": "Gose", "Dates": "", "State": "SC", "Brewery": "Westbrook", "Style": "Gose"}|{"City": "Woodbridge", "Availability": "", "Establishments": "", "Checkin": "False", "Distribution": "", "Beer": "Fuzzy Baby Ducks", "Dates": "", "State": "CT", "Brewery": "New England", "Style": "IPA"}|{"City": "Tampa", "Availability": "", "Establishments": "", "Checkin": "False", "Distribution": "", "Beer": "Jai Alai", "Dates": "", "State": "FL", "Brewery": "Cigar City", "Style": "IPA"}|{"City": "Fargo", "Availability": "", "Establishments": "", "Checkin": "False", "Distribution": "", "Beer": "Wood Chipper", "Dates": "", "State": "ND", "Brewery": "Fargo", "Style": "IPA"}|{"City": "Henderson", "Availability": "", "Establishments": "", "Checkin": "False", "Distribution": "", "Beer": "American Flyer", "Dates": "", "State": "NV", "Brewery": "Joseph James", "Style": "Lager"}|{"City": "Austin", "Availability": "", "Establishments": "", "Checkin": "False", "Distribution": "", "Beer": "The One They Call Zoe", "Dates": "", "State": "TX", "Brewery": "Hops & Grain", "Style": "Lager"}|{"City": "Cedar Rapids", "Availability": "", "Establishments": "", "Checkin": "False", "Distribution": "", "Beer": "The Disaster at Meux", "Dates": "", "State": "IA", "Brewery": "Lion Bridge", "Style": "Porter"}|{"City": "Spearfish", "Availability": "", "Establishments": "", "Checkin": "False", "Distribution": "", "Beer": "Pile o' Dirt", "Dates": "", "State": "SD", "Brewery": "Crow Peak", "Style": "Porter"}|{"City": "Park City", "Availability": "", "Establishments": "", "Checkin": "False", "Distribution": "", "Beer": "Polygamy Porter", "Dates": "", "State": "UT", "Brewery": "Wasatch", "Style": "Porter"}|{"City": "Hampton", "Availability": "", "Establishments": "", "Checkin": "False", "Distribution": "", "Beer": "Rhye IPA", "Dates": "", "State": "NH", "Brewery": "Smuttynose", "Style": "Rye"}|{"City": "Seattle", "Availability": "", "Establishments": "", "Checkin": "False", "Distribution": "", "Beer": "Bonfire", "Dates": "", "State": "WA", "Brewery": "Fremont", "Style": "Rye"}|{"City": "Brooklyn", "Availability": "", "Establishments": "", "Checkin": "False", "Distribution": "", "Beer": "Sour Bikini", "Dates": "", "State": "NY", "Brewery": "Evil Twin", "Style": "Sour"}|{"City": "Tulsa", "Availability": "", "Establishments": "", "Checkin": "False", "Distribution": "", "Beer": "Funky Gold Amarillo", "Dates": "", "State": "OK", "Brewery": "Prarie Artisan Ales", "Style": "Sour"}|{"City": "Asheville", "Availability": "", "Establishments": "", "Checkin": "False", "Distribution": "", "Beer": "Skillet Donut Stout", "Dates": "", "State": "NC", "Brewery": "Burial Beer", "Style": "Stout"}|{"City": "Jackson", "Availability": "", "Establishments": "", "Checkin": "False", "Distribution": "", "Beer": "Zonker", "Dates": "", "State": "WY", "Brewery": "Snake River", "Style": "Stout"}|{"City": "Fort Collins", "Availability": "", "Establishments": "", "Checkin": "False", "Distribution": "", "Beer": "St. Lupulin", "Dates": "", "State": "CO", "Brewery": "Odell", "Style": "Summer"}|{"City": "Somerdale", "Availability": "", "Establishments": "", "Checkin": "False", "Distribution": "", "Beer": "Farmhouse Summer", "Dates": "", "State": "NJ", "Brewery": "Flying Fish", "Style": "Summer"}|{"City": "Santa Fe", "Availability": "", "Establishments": "", "Checkin": "False", "Distribution": "", "Beer": "Hefeweizen", "Dates": "", "State": "NM", "Brewery": "Santa Fe", "Style": "Whit"}|{"City": "Atlanta", "Availability": "", "Establishments": "", "Checkin": "False", "Distribution": "", "Beer": "Waterkeeper Hefeweizen", "Dates": "", "State": "GA", "Brewery": "SweetWater", "Style": "Whit"}|{"City": "Juneau", "Availability": "", "Establishments": "", "Checkin": "False", "Distribution": "", "Beer": "Winter Ale", "Dates": "", "State": "AK", "Brewery": "Alaskan", "Style": "Winter/Christmas"}|{"City": "Boulder", "Availability": "", "Establishments": "", "Checkin": "False", "Distribution": "", "Beer": "Christmas", "Dates": "", "State": "CO", "Brewery": "Upslope", "Style": "Winter/Christmas"}|{"City": "Dexter", "Availability": "", "Establishments": "", "Checkin": "False", "Distribution": "", "Beer": "Noel de Calabaza", "Dates": "", "State": "MI", "Brewery": "Jolly Pumpkin", "Style": "Winter/Christmas"}|{"City": "Missoula", "Availability": "", "Establishments": "", "Checkin": "False", "Distribution": "", "Beer": "Powder Hound", "Dates": "", "State": "MT", "Brewery": "Big Sky", "Style": "Winter/Christmas"}|{"City": "Bend", "Availability": "", "Establishments": "", "Checkin": "False", "Distribution": "", "Beer": "Jubelale", "Dates": "", "State": "OR", "Brewery": "Deschutes", "Style": "Winter/Christmas"}|{"City": "Ft. Collins", "Availability": "", "Establishments": "", "Checkin": "True", "Distribution": "", "Beer": "Fat Tire", "Dates": "", "State": "CO", "Brewery": "New Belgium", "Style": "Amber"}|{"City": "Freeport", "Availability": "", "Establishments": "", "Checkin": "True", "Distribution": "", "Beer": "Zoe", "Dates": "", "State": "ME", "Brewery": "Maine", "Style": "Amber"}|{"City": "Chico", "Availability": "", "Establishments": "", "Checkin": "True", "Distribution": "", "Beer": "Pale Ale", "Dates": "", "State": "CA", "Brewery": "Sierra Nevada", "Style": "American Pale"}|{"City": "Chicago", "Availability": "", "Establishments": "", "Checkin": "True", "Distribution": "", "Beer": "Daisy Cutter", "Dates": "", "State": "IL", "Brewery": "Half Acre", "Style": "American Pale"}|{"City": "Munster", "Availability": "", "Establishments": "", "Checkin": "True", "Distribution": "", "Beer": "Zombie Dust", "Dates": "", "State": "IN", "Brewery": "Three Floyds", "Style": "American Pale"}|{"City": "Holland", "Availability": "", "Establishments": "", "Checkin": "True", "Distribution": "", "Beer": "Dragon's Milk", "Dates": "", "State": "MI", "Brewery": "New Holland", "Style": "Barrel Aged"}|{"City": "Breckenridge", "Availability": "", "Establishments": "", "Checkin": "True", "Distribution": "", "Beer": "471 IPA Barrel Series", "Dates": "", "State": "CO", "Brewery": "Breckenridge", "Style": "Barrel Aged"}|{"City": "Chicago", "Availability": "", "Establishments": "", "Checkin": "True", "Distribution": "", "Beer": "Bourbon County Brand Coffee Stout", "Dates": "", "State": "IL", "Brewery": "Goose Island", "Style": "Barrel Aged"}|{"City": "San Francisco", "Availability": "", "Establishments": "", "Checkin": "True", "Distribution": "", "Beer": "Back in Black", "Dates": "", "State": "CA", "Brewery": "21st Amendment", "Style": "Black IPA"}|{"City": "Grand Rapids", "Availability": "", "Establishments": "", "Checkin": "True", "Distribution": "", "Beer": "Kentucky Breakfast Stout (KBS)", "Dates": "", "State": "MI", "Brewery": "Founders", "Style": "Breakfast"}|{"City": "Providence", "Availability": "", "Establishments": "", "Checkin": "True", "Distribution": "", "Beer": "Autocrat Coffee Milk Stout", "Dates": "", "State": "RI", "Brewery": "Narragansett", "Style": "Breakfast"}|{"City": "Denver", "Availability": "", "Establishments": "", "Checkin": "True", "Distribution": "", "Beer": "Chocolate Oak Aged Yeti", "Dates": "", "State": "CO", "Brewery": "Great Divide", "Style": "Chocolate"}|{"City": "Kansas City", "Availability": "", "Establishments": "", "Checkin": "True", "Distribution": "", "Beer": "Chocolate Ale", "Dates": "", "State": "MO", "Brewery": "Boulevard", "Style": "Chocolate"}|{"City": "Crozet", "Availability": "", "Establishments": "", "Checkin": "True", "Distribution": "", "Beer": "Shakedown", "Dates": "", "State": "VA", "Brewery": "Starr Hill", "Style": "Chocolate"}|{"City": "Milton", "Availability": "", "Establishments": "", "Checkin": "True", "Distribution": "", "Beer": "90 Minute IPA", "Dates": "", "State": "DE", "Brewery": "Dogfish Head", "Style": "dIPA"}|{"City": "Oakland Park", "Availability": "", "Establishments": "", "Checkin": "True", "Distribution": "", "Beer": "Sweet Potato Casserole", "Dates": "", "State": "FL", "Brewery": "Funky Buddha", "Style": "Fall/Pumpkin"}|{"City": "Portland", "Availability": "", "Establishments": "", "Checkin": "True", "Distribution": "", "Beer": "Pumpkinhead", "Dates": "", "State": "ME", "Brewery": "Shipyard", "Style": "Fall/Pumpkin"}|{"City": "Kiln", "Availability": "", "Establishments": "", "Checkin": "True", "Distribution": "", "Beer": "Southern Pecan", "Dates": "", "State": "MS", "Brewery": "Lazy Magnolia", "Style": "Fall/Pumpkin"}|{"City": "Kansas City", "Availability": "", "Establishments": "", "Checkin": "True", "Distribution": "", "Beer": "Tank 7", "Dates": "", "State": "MO", "Brewery": "Boulevard", "Style": "Farmhouse/Saison"}|{"City": "Brooklyn", "Availability": "", "Establishments": "", "Checkin": "True", "Distribution": "", "Beer": "Sorachi Ace", "Dates": "", "State": "NY", "Brewery": "Brooklyn", "Style": "Farmhouse/Saison"}|{"City": "Cooperstown", "Availability": "", "Establishments": "", "Checkin": "True", "Distribution": "", "Beer": "Hennepin", "Dates": "", "State": "NY", "Brewery": "Ommegang", "Style": "Farmhouse/Saison"}|{"City": "San Diego", "Availability": "", "Establishments": "", "Checkin": "True", "Distribution": "", "Beer": "Grapefruit Sculpin", "Dates": "", "State": "CA", "Brewery": "Ballast Point", "Style": "Fruit"}|{"City": "Shiner", "Availability": "", "Establishments": "", "Checkin": "True", "Distribution": "", "Beer": "Ruby Redbird", "Dates": "", "State": "TX", "Brewery": "Shiner", "Style": "Fruit"}|{"City": "Eureka", "Availability": "", "Establishments": "", "Checkin": "True", "Distribution": "", "Beer": "Raspberry Brown", "Dates": "", "State": "CA", "Brewery": "Lost Coast", "Style": "Fruit"}|{"City": "Boonville", "Availability": "", "Establishments": "", "Checkin": "True", "Distribution": "", "Beer": "Blood Orange Gose", "Dates": "", "State": "CA", "Brewery": "Anderson Valley", "Style": "Gose"}|{"City": "Baltimore", "Availability": "", "Establishments": "", "Checkin": "True", "Distribution": "", "Beer": "Gose Gone Wild", "Dates": "", "State": "MD", "Brewery": "Stillwater Artisanal", "Style": "Gose"}|{"City": "Alpine", "Availability": "", "Establishments": "", "Checkin": "True", "Distribution": "", "Beer": "Pure Hoppiness", "Dates": "", "State": "CA", "Brewery": "Alpine", "Style": "IPA"}|{"City": "Kalamazoo", "Availability": "", "Establishments": "", "Checkin": "True", "Distribution": "", "Beer": "Two Hearted", "Dates": "", "State": "MI", "Brewery": "Bell's", "Style": "IPA"}|{"City": "Minneapolis", "Availability": "", "Establishments": "", "Checkin": "True", "Distribution": "", "Beer": "Hell", "Dates": "", "State": "MN", "Brewery": "Surly", "Style": "Lager"}|{"City": "Brooklyn", "Availability": "", "Establishments": "", "Checkin": "True", "Distribution": "", "Beer": "Lager", "Dates": "", "State": "NY", "Brewery": "Brooklyn", "Style": "Lager"}|{"City": "Roseland", "Availability": "", "Establishments": "", "Checkin": "True", "Distribution": "", "Beer": "Vienna Lager", "Dates": "", "State": "VA", "Brewery": "Devil's Backbone", "Style": "Lager"}|{"City": "Maui", "Availability": "", "Establishments": "", "Checkin": "True", "Distribution": "", "Beer": "Coconut Porter", "Dates": "", "State": "HI", "Brewery": "Maui", "Style": "Porter"}|{"City": "Cleveland", "Availability": "", "Establishments": "", "Checkin": "True", "Distribution": "", "Beer": "Edmund Fitzgerald", "Dates": "", "State": "OH", "Brewery": "Great Lakes", "Style": "Porter"}|{"City": "Washington", "Availability": "", "Establishments": "", "Checkin": "True", "Distribution": "", "Beer": "Rowdy", "Dates": "", "State": "DC", "Brewery": "Atlas", "Style": "Rye"}|{"City": "Athens", "Availability": "", "Establishments": "", "Checkin": "True", "Distribution": "", "Beer": "Rye Pale Ale", "Dates": "", "State": "GA", "Brewery": "Terrapin", "Style": "Rye"}|{"City": "Warrenville", "Availability": "", "Establishments": "", "Checkin": "True", "Distribution": "", "Beer": "Cane and Ebel", "Dates": "", "State": "IL", "Brewery": "Two Brothers", "Style": "Rye"}|{"City": "Ft. Collins", "Availability": "", "Establishments": "", "Checkin": "True", "Distribution": "", "Beer": "Le Terroir", "Dates": "", "State": "CO", "Brewery": "New Belgium", "Style": "Sour"}|{"City": "Milton", "Availability": "", "Establishments": "", "Checkin": "True", "Distribution": "", "Beer": "Festina Peche", "Dates": "", "State": "DE", "Brewery": "Dogfish Head", "Style": "Sour"}|{"City": "Salt Lake City", "Availability": "", "Establishments": "", "Checkin": "True", "Distribution": "", "Beer": "Birthday Suit", "Dates": "", "State": "UT", "Brewery": "Uinta", "Style": "Sour"}|{"City": "Louisville", "Availability": "", "Establishments": "", "Checkin": "True", "Distribution": "", "Beer": "35K", "Dates": "", "State": "KY", "Brewery": "Against the Grain", "Style": "Stout"}|{"City": "Farmville", "Availability": "", "Establishments": "", "Checkin": "True", "Distribution": "", "Beer": "Milk Stout", "Dates": "", "State": "NC", "Brewery": "Duck-Rabbit", "Style": "Stout"}|{"City": "Richmond", "Availability": "", "Establishments": "", "Checkin": "True", "Distribution": "", "Beer": "Gingerbread Stout", "Dates": "", "State": "VA", "Brewery": "Hardywood", "Style": "Stout"}|{"City": "Kalamazoo", "Availability": "", "Establishments": "", "Checkin": "True", "Distribution": "", "Beer": "Oberon", "Dates": "", "State": "MI", "Brewery": "Bell's", "Style": "Summer"}|{"City": "Cooperstown", "Availability": "", "Establishments": "", "Checkin": "True", "Distribution": "", "Beer": "Fleur de Houblon", "Dates": "", "State": "NY", "Brewery": "Ommegang", "Style": "Summer"}|{"City": "Downington", "Availability": "", "Establishments": "", "Checkin": "True", "Distribution": "", "Beer": "Summer Love", "Dates": "", "State": "PA", "Brewery": "Victory", "Style": "Summer"}|{"City": "Abita Springs", "Availability": "", "Establishments": "", "Checkin": "True", "Distribution": "", "Beer": "Purple Haze", "Dates": "", "State": "LA", "Brewery": "Abita", "Style": "Whit"}|{"City": "Portland", "Availability": "", "Establishments": "", "Checkin": "True", "Distribution": "", "Beer": "Hefeweizen", "Dates": "", "State": "OR", "Brewery": "Widmer Brothers", "Style": "Whit"}|{"City": "Alexandria", "Availability": "", "Establishments": "", "Checkin": "True", "Distribution": "", "Beer": "Optimal Wit", "Dates": "", "State": "VA", "Brewery": "Port City", "Style": "Whit"}|